pocl_binary_distribution-3.0.dist-info/WHEEL
pocl_binary_distribution-3.0.dist-info/METADATA
pocl_binary_distribution-3.0.dist-info/top_level.txt
pocl_binary_distribution-3.0.dist-info/RECORD
pyopencl/.libs/libpocl-21062cec.so
pyopencl/.libs/pocl.icd
pocl_binary_distribution/__init__.py
pocl_binary_distribution/.libs/libhwloc-4fb53721.so.15.0.2
pocl_binary_distribution/.libs/share/pocl/kernel-x86_64-unknown-linux-gnu-avx_f16c.bc
pocl_binary_distribution/.libs/share/pocl/kernel-x86_64-unknown-linux-gnu-sse2.bc
pocl_binary_distribution/.libs/share/pocl/kernel-x86_64-unknown-linux-gnu-avx2.bc
pocl_binary_distribution/.libs/share/pocl/kernel-x86_64-unknown-linux-gnu-avx.bc
pocl_binary_distribution/.libs/share/pocl/kernel-x86_64-unknown-linux-gnu-avx_fma4.bc
pocl_binary_distribution/.libs/share/pocl/kernel-x86_64-unknown-linux-gnu-ssse3.bc
pocl_binary_distribution/.libs/share/pocl/kernel-x86_64-unknown-linux-gnu-avx512.bc
pocl_binary_distribution/.libs/share/pocl/kernel-x86_64-unknown-linux-gnu-sse41.bc
pocl_binary_distribution/.libs/share/pocl/licenses/HWLOC.COPYING
pocl_binary_distribution/.libs/share/pocl/licenses/LLVM_LICENSE.txt
pocl_binary_distribution/.libs/share/pocl/licenses/POCL.COPYING
pocl_binary_distribution/.libs/share/pocl/include/opencl-c.h
pocl_binary_distribution/.libs/share/pocl/include/_kernel_c.h
pocl_binary_distribution/.libs/share/pocl/include/_kernel_constants.h
pocl_binary_distribution/.libs/share/pocl/include/_libclang_versions_checks.h
pocl_binary_distribution/.libs/share/pocl/include/pocl_image_types.h
pocl_binary_distribution/.libs/share/pocl/include/opencl-c-base.h
pocl_binary_distribution/.libs/share/pocl/include/_builtin_renames.h
pocl_binary_distribution/.libs/share/pocl/include/pocl_types.h
pocl_binary_distribution/.libs/share/pocl/include/_kernel.h
pocl_binary_distribution/.libs/share/pocl/include/_enable_all_exts.h
pocl_binary_distribution/.libs/share/pocl/include/_clang_opencl.h
pocl_binary_distribution/.libs/share/pocl/include/pocl.h
pocl_binary_distribution/.libs/share/pocl/include/pocl_spir.h
pocl_binary_distribution/.libs/share/pocl/include/pocl_device.h
