Metadata-Version: 2.1
Name: pocl-binary-distribution
Version: 3.0
Summary: Pocl Binary Distribution to be used with PyOpenCL
Home-page: https://github.com/isuruf/pocl-binary-distribution
Author: Isuru Fernando
Author-email: isuruf@gmail.com
